{
  "anime_id" : 1304,
  "characters" : {
    "APPEARANCE" : [ {
      "character_id" : 89914,
      "name" : "Bob Reily Honbuchou",
      "type" : "CHARACTER"
    }, {
      "character_id" : 89902,
      "name" : "Ivan Hassan",
      "type" : "CHARACTER"
    }, {
      "character_id" : 89905,
      "name" : "Kazama Shougun",
      "type" : "CHARACTER"
    }, {
      "character_id" : 89906,
      "name" : "Kerberos",
      "type" : "CHARACTER"
    }, {
      "character_id" : 89911,
      "name" : "Serem",
      "type" : "CHARACTER"
    }, {
      "character_id" : 89913,
      "name" : "Tomioka",
      "type" : "CHARACTER"
    }, {
      "character_id" : 89919,
      "name" : "Angel Arms",
      "type" : "ORGANIZATION"
    } ],
    "MAIN" : [ {
      "character_id" : 89900,
      "name" : "Alissa Takakura",
      "type" : "CHARACTER"
    }, {
      "character_id" : 89915,
      "name" : "Marcia Asano",
      "type" : "CHARACTER"
    }, {
      "character_id" : 89916,
      "name" : "Michelle Iga",
      "type" : "CHARACTER"
    }, {
      "character_id" : 89908,
      "name" : "Silvia Kakihana",
      "type" : "CHARACTER"
    }, {
      "character_id" : 89912,
      "name" : "Takako Houraiji",
      "type" : "CHARACTER"
    }, {
      "character_id" : 89917,
      "name" : "Yung Kei",
      "type" : "CHARACTER"
    } ],
    "SECONDARY" : [ {
      "character_id" : 89901,
      "name" : "Ali Jaheeve Hassan",
      "type" : "CHARACTER"
    }, {
      "character_id" : 89904,
      "name" : "Endou Keibu",
      "type" : "CHARACTER"
    }, {
      "character_id" : 89907,
      "name" : "Gouman",
      "type" : "CHARACTER"
    }, {
      "character_id" : 89909,
      "name" : "Jean Luc Skinner",
      "type" : "CHARACTER"
    }, {
      "character_id" : 89918,
      "name" : "Ryou Saeki",
      "type" : "CHARACTER"
    }, {
      "character_id" : 89910,
      "name" : "Sumeragi Taii",
      "type" : "CHARACTER"
    }, {
      "character_id" : 89903,
      "name" : "Won Shichou",
      "type" : "CHARACTER"
    } ]
  },
  "creators" : {
    "1169" : [ {
      "name" : "Sanctuary",
      "type" : "WORK"
    } ],
    "1743" : [ {
      "name" : "Yatabe Katsuyoshi",
      "type" : "DIRECTOR"
    } ],
    "6176" : [ {
      "name" : "Aoki Tetsurou",
      "type" : "CHARACTER_DESIGN"
    } ],
    "6400" : [ {
      "name" : "Iwai Yuuki",
      "type" : "CHARACTER_DESIGN"
    } ],
    "29745" : [ {
      "name" : "Tominaga Yutaka",
      "type" : "MUSIC"
    } ],
    "37778" : [ {
      "name" : "Amasawa Akira",
      "type" : "ORIGINAL_WORK"
    } ]
  },
  "description" : "In 2100, the newly built Bayside City serves as Japan`s premier international port. The Angel Arms Company is established by a former policewoman named Takako, to help wage war on terrorism with armed security suits.\nWhen the mayor is assassinated, the women of Angel Arms end up protecting the evil crime-lord Hassan, in hopes that his information will help bring down a global terror ring. Takako`s back is to the wall as a band of criminals plot to kill Hassan, and the organization`s leader is revealed to be the former lover of Angel Arms` own Alisa.\nSource: AnimeNfo",
  "end_date" : "1999-03-20",
  "episodes" : {
    "REGULAR" : [ {
      "air_date" : "1999-03-20",
      "episode_id" : 13860,
      "length" : 85,
      "number" : 1,
      "rating" : {
        "rating" : 4.71,
        "total" : 1
      },
      "recap" : false,
      "titles" : [ {
        "language" : "ENGLISH",
        "title" : "Complete Movie"
      } ],
      "type" : "REGULAR"
    }, {
      "air_date" : "1999-03-20",
      "episode_id" : 36464,
      "length" : 45,
      "number" : 2,
      "recap" : false,
      "titles" : [ {
        "language" : "ENGLISH",
        "title" : "Part 1 of 2"
      } ],
      "type" : "REGULAR"
    }, {
      "air_date" : "1999-03-20",
      "episode_id" : 36465,
      "length" : 40,
      "number" : 3,
      "recap" : false,
      "titles" : [ {
        "language" : "ENGLISH",
        "title" : "Part 2 of 2"
      } ],
      "type" : "REGULAR"
    } ]
  },
  "ratings" : {
    "PERMANENT" : {
      "rating" : 3.1,
      "total" : 372
    },
    "REVIEW" : {
      "rating" : 3.83,
      "total" : 2
    },
    "TEMPORARY" : {
      "rating" : 5.47,
      "total" : 372
    }
  },
  "resources" : {
    "ALL_CINEMA" : [ "125556" ],
    "ANIME_NFO" : [ "1092,tmssto" ],
    "ANN" : [ "368" ],
    "IMDB" : [ "tt0331508" ],
    "MAL" : [ "1160" ],
    "SYOBOI" : [ "924" ],
    "WIKIPEDIA_JP" : [ "ガンドレス" ]
  },
  "start_date" : "1999-03-20",
  "tags" : {
    "36" : {
      "info_box" : false,
      "name" : "military",
      "parent_tag_id" : 2607,
      "spoiler" : false,
      "verified" : false,
      "weight" : 200
    },
    "760" : {
      "info_box" : false,
      "name" : "robot helper",
      "parent_tag_id" : 2274,
      "spoiler" : false,
      "verified" : false,
      "weight" : 300
    },
    "2180" : {
      "info_box" : true,
      "name" : "cyborg",
      "parent_tag_id" : 2636,
      "spoiler" : false,
      "verified" : false,
      "weight" : 400
    },
    "2274" : {
      "info_box" : false,
      "name" : "robot",
      "parent_tag_id" : 2638,
      "spoiler" : false,
      "verified" : false,
      "weight" : 0
    },
    "2604" : {
      "info_box" : false,
      "name" : "content indicators",
      "spoiler" : false,
      "verified" : false,
      "weight" : 0
    },
    "2605" : {
      "info_box" : false,
      "name" : "dynamic",
      "spoiler" : false,
      "verified" : false,
      "weight" : 0
    },
    "2607" : {
      "info_box" : false,
      "name" : "themes",
      "spoiler" : false,
      "verified" : false,
      "weight" : 0
    },
    "2610" : {
      "info_box" : false,
      "name" : "setting",
      "spoiler" : false,
      "verified" : false,
      "weight" : 0
    },
    "2611" : {
      "info_box" : false,
      "name" : "elements",
      "spoiler" : false,
      "verified" : false,
      "weight" : 0
    },
    "2612" : {
      "info_box" : false,
      "name" : "time",
      "parent_tag_id" : 2610,
      "spoiler" : false,
      "verified" : false,
      "weight" : 0
    },
    "2613" : {
      "info_box" : false,
      "name" : "place",
      "parent_tag_id" : 2610,
      "spoiler" : false,
      "verified" : false,
      "weight" : 0
    },
    "2618" : {
      "info_box" : false,
      "name" : "collateral damage",
      "parent_tag_id" : 2841,
      "spoiler" : false,
      "verified" : false,
      "weight" : 0
    },
    "2619" : {
      "info_box" : true,
      "name" : "gunfights",
      "parent_tag_id" : 2841,
      "spoiler" : false,
      "verified" : false,
      "weight" : 400
    },
    "2626" : {
      "info_box" : false,
      "name" : "future",
      "parent_tag_id" : 2612,
      "spoiler" : false,
      "verified" : false,
      "weight" : 600
    },
    "2628" : {
      "info_box" : false,
      "name" : "fictional location",
      "parent_tag_id" : 2613,
      "spoiler" : false,
      "verified" : false,
      "weight" : 0
    },
    "2630" : {
      "info_box" : false,
      "name" : "Earth",
      "parent_tag_id" : 2613,
      "spoiler" : false,
      "verified" : false,
      "weight" : 600
    },
    "2636" : {
      "info_box" : true,
      "name" : "human enhancement",
      "parent_tag_id" : 2846,
      "spoiler" : false,
      "verified" : false,
      "weight" : 400
    },
    "2638" : {
      "info_box" : true,
      "name" : "mecha",
      "parent_tag_id" : 2846,
      "spoiler" : false,
      "verified" : false,
      "weight" : 600
    },
    "2645" : {
      "info_box" : true,
      "name" : "piloted robot",
      "parent_tag_id" : 2274,
      "spoiler" : false,
      "verified" : false,
      "weight" : 600
    },
    "2672" : {
      "info_box" : false,
      "name" : "Japan",
      "parent_tag_id" : 2834,
      "spoiler" : false,
      "verified" : false,
      "weight" : 600
    },
    "2749" : {
      "info_box" : false,
      "name" : "nudity",
      "parent_tag_id" : 2604,
      "spoiler" : false,
      "verified" : false,
      "weight" : 300
    },
    "2750" : {
      "info_box" : true,
      "name" : "violence",
      "parent_tag_id" : 2604,
      "spoiler" : false,
      "verified" : false,
      "weight" : 400
    },
    "2791" : {
      "info_box" : false,
      "name" : "stereotypes",
      "parent_tag_id" : 6230,
      "spoiler" : false,
      "verified" : false,
      "weight" : 200
    },
    "2834" : {
      "info_box" : false,
      "name" : "Asia",
      "parent_tag_id" : 2630,
      "spoiler" : false,
      "verified" : false,
      "weight" : 600
    },
    "2837" : {
      "info_box" : false,
      "name" : "floating island",
      "parent_tag_id" : 2628,
      "spoiler" : false,
      "verified" : false,
      "weight" : 200
    },
    "2841" : {
      "info_box" : true,
      "name" : "action",
      "parent_tag_id" : 2611,
      "spoiler" : false,
      "verified" : false,
      "weight" : 600
    },
    "2846" : {
      "info_box" : true,
      "name" : "science fiction",
      "parent_tag_id" : 7050,
      "spoiler" : false,
      "verified" : false,
      "weight" : 600
    },
    "2856" : {
      "info_box" : false,
      "name" : "ecchi",
      "parent_tag_id" : 2611,
      "spoiler" : false,
      "verified" : false,
      "weight" : 100
    },
    "2858" : {
      "info_box" : false,
      "name" : "romance",
      "parent_tag_id" : 2611,
      "spoiler" : false,
      "verified" : false,
      "weight" : 100
    },
    "2861" : {
      "info_box" : false,
      "name" : "cyberpunk",
      "parent_tag_id" : 2846,
      "spoiler" : false,
      "verified" : false,
      "weight" : 300
    },
    "2867" : {
      "info_box" : false,
      "name" : "politics",
      "parent_tag_id" : 2607,
      "spoiler" : false,
      "verified" : false,
      "weight" : 200
    },
    "2872" : {
      "info_box" : false,
      "name" : "crime",
      "parent_tag_id" : 2607,
      "spoiler" : false,
      "verified" : false,
      "weight" : 400
    },
    "2874" : {
      "info_box" : false,
      "name" : "disaster",
      "parent_tag_id" : 2607,
      "spoiler" : false,
      "verified" : false,
      "weight" : 400
    },
    "2885" : {
      "info_box" : false,
      "name" : "law and order",
      "parent_tag_id" : 2607,
      "spoiler" : false,
      "verified" : false,
      "weight" : 200
    },
    "2887" : {
      "info_box" : true,
      "name" : "tragedy",
      "parent_tag_id" : 2611,
      "spoiler" : false,
      "verified" : false,
      "weight" : 400
    },
    "2897" : {
      "info_box" : false,
      "name" : "police",
      "parent_tag_id" : 2885,
      "spoiler" : false,
      "verified" : false,
      "weight" : 200
    },
    "2898" : {
      "info_box" : false,
      "name" : "special squads",
      "parent_tag_id" : 2885,
      "spoiler" : false,
      "verified" : false,
      "weight" : 400
    },
    "2931" : {
      "info_box" : false,
      "name" : "unsorted",
      "spoiler" : false,
      "verified" : false,
      "weight" : 0
    },
    "3097" : {
      "info_box" : false,
      "name" : "underwater",
      "parent_tag_id" : 2613,
      "spoiler" : false,
      "verified" : false,
      "weight" : 100
    },
    "3148" : {
      "info_box" : false,
      "name" : "open-ended",
      "parent_tag_id" : 6246,
      "spoiler" : false,
      "verified" : false,
      "weight" : 0
    },
    "3618" : {
      "info_box" : false,
      "name" : "ocean",
      "parent_tag_id" : 2613,
      "spoiler" : false,
      "verified" : false,
      "weight" : 100
    },
    "3696" : {
      "info_box" : false,
      "name" : "off-model animation",
      "parent_tag_id" : 6151,
      "spoiler" : false,
      "verified" : false,
      "weight" : 0
    },
    "4227" : {
      "info_box" : false,
      "name" : "detailed landscapes",
      "parent_tag_id" : 6151,
      "spoiler" : false,
      "verified" : false,
      "weight" : 0
    },
    "4274" : {
      "info_box" : false,
      "name" : "hidden agenda",
      "parent_tag_id" : 2931,
      "spoiler" : false,
      "verified" : false,
      "weight" : 0
    },
    "4278" : {
      "info_box" : false,
      "name" : "stand-alone movie",
      "parent_tag_id" : 6151,
      "spoiler" : false,
      "verified" : false,
      "weight" : 0
    },
    "5935" : {
      "info_box" : false,
      "name" : "ass-kicking girls",
      "parent_tag_id" : 6233,
      "spoiler" : false,
      "verified" : false,
      "weight" : 0
    },
    "6151" : {
      "info_box" : false,
      "name" : "technical aspects",
      "spoiler" : false,
      "verified" : false,
      "weight" : 0
    },
    "6173" : {
      "info_box" : false,
      "name" : "origin",
      "spoiler" : false,
      "verified" : false,
      "weight" : 0
    },
    "6230" : {
      "info_box" : false,
      "name" : "cast",
      "parent_tag_id" : 2605,
      "spoiler" : false,
      "verified" : false,
      "weight" : 0
    },
    "6233" : {
      "info_box" : false,
      "name" : "tropes",
      "parent_tag_id" : 2611,
      "spoiler" : false,
      "verified" : false,
      "weight" : 0
    },
    "6246" : {
      "info_box" : false,
      "name" : "ending",
      "parent_tag_id" : 2605,
      "spoiler" : false,
      "verified" : false,
      "weight" : 0
    },
    "6254" : {
      "info_box" : false,
      "name" : "terrorism",
      "parent_tag_id" : 2872,
      "spoiler" : false,
      "verified" : false,
      "weight" : 400
    },
    "7050" : {
      "info_box" : false,
      "name" : "speculative fiction",
      "parent_tag_id" : 2611,
      "spoiler" : false,
      "verified" : false,
      "weight" : 0
    },
    "7885" : {
      "info_box" : false,
      "name" : "Japanese production",
      "parent_tag_id" : 6173,
      "spoiler" : false,
      "verified" : false,
      "weight" : 0
    }
  },
  "titles" : [ {
    "language" : "JAPANESE_TRANSLITERATED",
    "title" : "Gundress",
    "type" : "MAIN"
  }, {
    "language" : "ENGLISH",
    "title" : "Gundress",
    "type" : "OFFICIAL"
  }, {
    "language" : "JAPANESE",
    "title" : "ガンドレス",
    "type" : "OFFICIAL"
  }, {
    "language" : "JAPANESE",
    "title" : "GUNNDRESS",
    "type" : "SYNONYM"
  }, {
    "language" : "KOREAN",
    "title" : "건드레스",
    "type" : "SYNONYM"
  } ],
  "type" : "MOVIE"
}