{
  "anime_id" : 15604,
  "characters" : {
    "APPEARANCE" : [ {
      "character_id" : 119359,
      "name" : "Alexander",
      "type" : "CHARACTER"
    }, {
      "character_id" : 119260,
      "name" : "Frey Randall",
      "type" : "CHARACTER"
    }, {
      "character_id" : 119261,
      "name" : "Ginger Tucker",
      "type" : "CHARACTER"
    }, {
      "character_id" : 123121,
      "name" : "Pochi",
      "type" : "CHARACTER"
    } ],
    "MAIN" : [ {
      "character_id" : 106308,
      "name" : "Catarina Claes",
      "type" : "CHARACTER"
    } ],
    "SECONDARY" : [ {
      "character_id" : 108095,
      "name" : "Alan Stuart",
      "type" : "CHARACTER"
    }, {
      "character_id" : 109132,
      "name" : "Anne Shelley",
      "type" : "CHARACTER"
    }, {
      "character_id" : 108100,
      "name" : "Geordo Stuart",
      "type" : "CHARACTER"
    }, {
      "character_id" : 116084,
      "name" : "Ian Stuart",
      "type" : "CHARACTER"
    }, {
      "character_id" : 116085,
      "name" : "Jeffrey Stuart",
      "type" : "CHARACTER"
    }, {
      "character_id" : 108098,
      "name" : "Keith Claes",
      "type" : "CHARACTER"
    }, {
      "character_id" : 108627,
      "name" : "Maria Campbell",
      "type" : "CHARACTER"
    }, {
      "character_id" : 108628,
      "name" : "Mary Hunt",
      "type" : "CHARACTER"
    }, {
      "character_id" : 108102,
      "name" : "Nicol Ascart",
      "type" : "CHARACTER"
    }, {
      "character_id" : 109133,
      "name" : "Raphael Walt",
      "type" : "CHARACTER"
    }, {
      "character_id" : 117456,
      "name" : "Rufus Brode",
      "type" : "CHARACTER"
    }, {
      "character_id" : 119645,
      "name" : "Sara",
      "type" : "CHARACTER"
    }, {
      "character_id" : 119644,
      "name" : "Sasaki Atsuko",
      "type" : "CHARACTER"
    }, {
      "character_id" : 116087,
      "name" : "Selena Berg",
      "type" : "CHARACTER"
    }, {
      "character_id" : 108626,
      "name" : "Sophia Ascart",
      "type" : "CHARACTER"
    }, {
      "character_id" : 116086,
      "name" : "Susanna Randall",
      "type" : "CHARACTER"
    } ]
  },
  "creators" : {
    "2900" : [ {
      "name" : "Silver Link",
      "type" : "ANIMATION_WORK"
    } ],
    "3779" : [ {
      "name" : "Ooshima Miwa",
      "type" : "CHARACTER_DESIGN"
    }, {
      "name" : "Ooshima Miwa",
      "type" : "CHIEF_ANIMATION_DIRECTION"
    } ],
    "21374" : [ {
      "name" : "Shimizu Megumi",
      "type" : "SERIES_COMPOSITION"
    } ],
    "27445" : [ {
      "name" : "Inoue Keisuke",
      "type" : "DIRECTOR"
    } ],
    "43277" : [ {
      "name" : "Kanematsu Shuu",
      "type" : "MUSIC"
    } ],
    "48386" : [ {
      "name" : "Tabuchi Natsumi",
      "type" : "MUSIC"
    } ],
    "48387" : [ {
      "name" : "Nakamura Hanae",
      "type" : "MUSIC"
    } ],
    "56507" : [ {
      "name" : "Yamaguchi Satoru",
      "type" : "ORIGINAL_WORK"
    } ],
    "56514" : [ {
      "name" : "Sakurai Miki",
      "type" : "MUSIC"
    } ],
    "59230" : [ {
      "name" : "Saiki Tatsuhiko",
      "type" : "MUSIC"
    } ],
    "64063" : [ {
      "name" : "Aoki Sayaka",
      "type" : "MUSIC"
    } ],
    "64064" : [ {
      "name" : "Nakajima Junko",
      "type" : "MUSIC"
    } ],
    "64066" : [ {
      "name" : "Sakuma Kanade",
      "type" : "MUSIC"
    } ]
  },
  "description" : "* Based on a light novel series written by http://anidb.net/cr56507 [Yamaguchi Satoru] and illustrated by http://anidb.net/cr56506 [Hidaka Nami].\nWealthy heiress http://anidb.net/ch106308 [Catarina Claes] is hit in the head with a rock and recovers the memories of her past life.\nIt turns out the world she lives in is the world of the game Fortune Lover, an otome game she was obsessed with in her past life... but she`s been cast as the villain character who tries to foil the protagonist`s romances!\nThe best ending the game has for Catarina is exile, and the worst, death! She`ll have to find a way to avoid triggering the flags of doom, and make her own happy future!\nThe misunderstanding-based screwball love comedy now begins!\nSource: Crunchyroll",
  "end_date" : "2021-09-18",
  "episodes" : {
    "REGULAR" : [ {
      "air_date" : "2021-07-03",
      "description" : "Catarina Claes, the daughter of a duke, successfully avoided all of her doom flags and is now enjoying her school life. One day, she learns that the school festival is coming up, and she`s psyched to experience it. Geordo and the other student council members are swamped with festival preparations, so Catarina is left on her own to wonder what kinds of foods she`ll find at the event.\nSource: crunchyroll",
      "episode_id" : 241211,
      "length" : 25,
      "number" : 1,
      "rating" : {
        "rating" : 4.68,
        "total" : 5
      },
      "recap" : false,
      "resources" : {
        "CRUNCHY_ROLL" : [ "G0DUN99P1" ]
      },
      "titles" : [ {
        "language" : "JAPANESE_TRANSLITERATED",
        "title" : "Hametsu Flag o Kaihi Shita node Bunkasai de Ukarete Shimatta..."
      }, {
        "language" : "ENGLISH",
        "title" : "I Avoided My Doom Flags, So I Got Carried Away at the Cultural Festival..."
      }, {
        "language" : "FRENCH",
        "title" : "J’ai évité mon destin funeste mais je me suis laissé emporter au festival culturel…"
      }, {
        "language" : "ARABIC",
        "title" : "تفاديتُ أمارات موتي فانجرفتُ بفعاليات المهرجان الثقافي"
      }, {
        "language" : "JAPANESE",
        "title" : "破滅フラグを回避したので文化祭で浮かれてしまった…"
      } ],
      "type" : "REGULAR"
    }, {
      "air_date" : "2021-07-10",
      "description" : "One of the actors in the play being put on by the student council is injured, and the search is on for an emergency stand-in. As the opening of the curtain draws nearer and nearer, Catarina ends up agreeing to fill the role at Sophia`s request. She`s given a script with a story that sounds very familiar, and then her time comes to take the stage.\nSource: crunchyroll",
      "episode_id" : 241212,
      "length" : 25,
      "number" : 2,
      "rating" : {
        "rating" : 5.67,
        "total" : 4
      },
      "recap" : false,
      "resources" : {
        "CRUNCHY_ROLL" : [ "GEVUZ88MM" ]
      },
      "titles" : [ {
        "language" : "JAPANESE_TRANSLITERATED",
        "title" : "Akuyaku ni Natte Shimatta..."
      }, {
        "language" : "ENGLISH",
        "title" : "I Turned Into a Villainess..."
      }, {
        "language" : "FRENCH",
        "title" : "Je suis devenue la méchante rivale..."
      }, {
        "language" : "ARABIC",
        "title" : "أمسيتُ شريرًا/شريرة"
      }, {
        "language" : "JAPANESE",
        "title" : "悪役になってしまった..."
      } ],
      "type" : "REGULAR"
    }, {
      "air_date" : "2021-07-17",
      "description" : "Catarina is kidnapped by someone while on her way to the ball, but after awakening in an unfamiliar room, she struggles to fully grasp her situation and doesn`t seem to realize she`s been kidnapped. Even when the kidnapper shows up to see her in person and she asks why she was kidnapped, her questions are easily dodged. Meanwhile, Geordo receives a letter from the kidnapper and immediately begins an investigation to find and rescue Catarina.\nSource: crunchyroll",
      "episode_id" : 241213,
      "length" : 25,
      "number" : 3,
      "rating" : {
        "rating" : 4.19,
        "total" : 3
      },
      "recap" : false,
      "resources" : {
        "CRUNCHY_ROLL" : [ "G7PU4WWEQ" ]
      },
      "titles" : [ {
        "language" : "ENGLISH",
        "title" : "I Was Captured..."
      }, {
        "language" : "FRENCH",
        "title" : "Oh non, me voilà prisonnière..."
      }, {
        "language" : "JAPANESE_TRANSLITERATED",
        "title" : "Torawarenomi ni Natte Shimatta..."
      }, {
        "language" : "ARABIC",
        "title" : "حُبِست"
      }, {
        "language" : "JAPANESE",
        "title" : "囚われの身になってしまった..."
      } ],
      "type" : "REGULAR"
    }, {
      "air_date" : "2021-07-24",
      "description" : "The one behind the kidnapping of Catarina Claes turns out to be someone that nobody expected. Catarina is shocked to learn the true reason why he kidnapped her, but he`s so moved by her cheerful demeanor that he begins to tell her more and more about himself. As he does, Catarina proposes an idea...\nSource: crunchyroll",
      "episode_id" : 241214,
      "length" : 25,
      "number" : 4,
      "rating" : {
        "rating" : 6.94,
        "total" : 4
      },
      "recap" : false,
      "resources" : {
        "CRUNCHY_ROLL" : [ "G9DUEDDJ3" ]
      },
      "titles" : [ {
        "language" : "ENGLISH",
        "title" : "I Had a Friendly Tea Time with an Attractive Butler..."
      }, {
        "language" : "JAPANESE_TRANSLITERATED",
        "title" : "Iroppoi Shitsuji to Nakayoku Ocha o Shite Shimatta..."
      }, {
        "language" : "FRENCH",
        "title" : "J`ai dû prendre le thé avec un majordome attirant..."
      }, {
        "language" : "ARABIC",
        "title" : "تناولت الشاي مع كبير خدم جذاب"
      }, {
        "language" : "JAPANESE",
        "title" : "色っぽい執事と仲良くお茶をしてしまった..."
      } ],
      "type" : "REGULAR"
    }, {
      "air_date" : "2021-07-31",
      "description" : "The day after the resolution of Catarina Claes`s kidnapping, the first prince, Jeffrey Stuart, passionately speaks of his love for his younger brothers to his fiancée, Susanna Randall. At the same time, Geordo and Alan are in the student council office, reminiscing about their childhood days with their older brothers.\nSource: crunchyroll",
      "episode_id" : 242158,
      "length" : 25,
      "number" : 5,
      "rating" : {
        "rating" : 2.74,
        "total" : 6
      },
      "recap" : false,
      "resources" : {
        "CRUNCHY_ROLL" : [ "GX9UQKKXZ" ]
      },
      "titles" : [ {
        "language" : "ENGLISH",
        "title" : "Love for the Younger Brothers Poured Forth..."
      }, {
        "language" : "JAPANESE_TRANSLITERATED",
        "title" : "Otouto-tachi e no Ai ga Afurete Shimatta..."
      }, {
        "language" : "FRENCH",
        "title" : "Un amour un peu trop débordant envers ses petits frères..."
      }, {
        "language" : "ARABIC",
        "title" : "حب للإخوة الصغار يُعَبَّر"
      }, {
        "language" : "JAPANESE",
        "title" : "弟たちへの愛が溢れてしまった..."
      } ],
      "type" : "REGULAR"
    }, {
      "air_date" : "2021-08-07",
      "description" : "Catarina is overwhelmed by Geordo`s suddenly passionate advances. Since she had no romantic experience in her previous life, either, she has no idea what to do. When she receives an invitation to stay at the royal palace villa, she`s still unable to sort out her feelings, and upon arriving there, she learns that the nearby forest is rumored to be haunted by a ghost.\nSource: crunchyroll",
      "episode_id" : 242159,
      "length" : 25,
      "number" : 6,
      "rating" : {
        "rating" : 2.0,
        "total" : 5
      },
      "recap" : false,
      "resources" : {
        "CRUNCHY_ROLL" : [ "G4VUQMM91" ]
      },
      "titles" : [ {
        "language" : "JAPANESE_TRANSLITERATED",
        "title" : "Hito Natsu no Bouken o Shite Shimatta..."
      }, {
        "language" : "ENGLISH",
        "title" : "I Had a Summer Adventure..."
      }, {
        "language" : "FRENCH",
        "title" : "J`ai tout lâché pour une aventure d`un été..."
      }, {
        "language" : "ARABIC",
        "title" : "قمت بمغامرة صيفيّة"
      }, {
        "language" : "JAPANESE",
        "title" : "ひと夏の冒険をしてしまった..."
      } ],
      "type" : "REGULAR"
    }, {
      "air_date" : "2021-08-14",
      "description" : "Raphael Wolt, an employee at the Department of Magic, welcomes Catarina and her friends for a tour of the facility. Lana leads them in an experiment on a magic tool she recently acquired from an antiquarian: a so-called \"wish-granting doll house.\" The moment she sees the old, run-down doll house, Catarina can`t help opening the tightly shut front door...\nSource: crunchyroll",
      "episode_id" : 242160,
      "length" : 25,
      "number" : 7,
      "rating" : {
        "rating" : 2.48,
        "total" : 4
      },
      "recap" : false,
      "resources" : {
        "CRUNCHY_ROLL" : [ "G14U4XXD1" ]
      },
      "titles" : [ {
        "language" : "ENGLISH",
        "title" : "My Wish Was Granted..."
      }, {
        "language" : "JAPANESE_TRANSLITERATED",
        "title" : "Negai ga Kanatte Shimatta..."
      }, {
        "language" : "FRENCH",
        "title" : "Oups, mon vœu a été exaucé..."
      }, {
        "language" : "ARABIC",
        "title" : "تحقق أمنيتي"
      }, {
        "language" : "JAPANESE",
        "title" : "願いが叶ってしまった..."
      } ],
      "type" : "REGULAR"
    }, {
      "air_date" : "2021-08-21",
      "description" : "Nicol makes the decision to go through with an arranged marriage. Although he meets many prospective partners, all he can think about while talking to them is Catarina, so none of them get past the first meeting. Then, one day, his sister Sophia recommends that he read some romance novels for a change of pace.\nSource: crunchyroll",
      "episode_id" : 242161,
      "length" : 25,
      "number" : 8,
      "rating" : {
        "rating" : 4.91,
        "total" : 5
      },
      "recap" : false,
      "resources" : {
        "CRUNCHY_ROLL" : [ "GJWU2JJ3W" ]
      },
      "titles" : [ {
        "language" : "ENGLISH",
        "title" : "I Had an Arranged Marriage Meeting..."
      }, {
        "language" : "FRENCH",
        "title" : "Oh non, un autre mariage arrangé..."
      }, {
        "language" : "JAPANESE_TRANSLITERATED",
        "title" : "Omiai Shite Shimatta..."
      }, {
        "language" : "ARABIC",
        "title" : "حضرت لقاء زواج مدبّر"
      }, {
        "language" : "JAPANESE",
        "title" : "お見合いしてしまった..."
      } ],
      "type" : "REGULAR"
    }, {
      "air_date" : "2021-08-28",
      "description" : "Catarina is feeling thrown off by her sudden awareness of Geordo, so when she`s back at home during a break from school, she spends her time working her fields for a change of pace. When she`s done, she heads to Keith`s room to show him the vegetables she`s grown... but Keith isn`t there, and instead she finds a letter in his room saying that he`s running away.\nSource: crunchyroll",
      "episode_id" : 243165,
      "length" : 25,
      "number" : 9,
      "rating" : {
        "rating" : 3.67,
        "total" : 4
      },
      "recap" : false,
      "resources" : {
        "CRUNCHY_ROLL" : [ "GN7UDWWQX" ]
      },
      "titles" : [ {
        "language" : "ENGLISH",
        "title" : "Keith Disappeared... Part 1"
      }, {
        "language" : "JAPANESE_TRANSLITERATED",
        "title" : "Keith ga Inakunatte Shimatta... Zenpen"
      }, {
        "language" : "FRENCH",
        "title" : "Oups, Keith a disparu… (1re partie)"
      }, {
        "language" : "JAPANESE",
        "title" : "キースがいなくなってしまった... 前編"
      } ],
      "type" : "REGULAR"
    }, {
      "air_date" : "2021-09-04",
      "description" : "Catarina and a few of her friends set out on a journey to find Keith, assisted by Larna. Catarina still believes Keith left because of her. She tries her hardest to find some sort of clue in the first town they stop in, but there`s no useful information to be found. In the midst of all this, the captured Keith worries about the sister he left behind.\nSource: crunchyroll",
      "episode_id" : 243166,
      "length" : 25,
      "number" : 10,
      "rating" : {
        "rating" : 4.24,
        "total" : 4
      },
      "recap" : false,
      "resources" : {
        "CRUNCHY_ROLL" : [ "GK9U38812" ]
      },
      "titles" : [ {
        "language" : "ENGLISH",
        "title" : "Keith Disappeared... Part 2"
      }, {
        "language" : "JAPANESE_TRANSLITERATED",
        "title" : "Keith ga Inakunatte Shimatta... Chuuhen"
      }, {
        "language" : "FRENCH",
        "title" : "Oups, Keith a disparu… (2e partie)"
      }, {
        "language" : "ARABIC",
        "title" : "كيث اختفى... الجزء 2"
      }, {
        "language" : "JAPANESE",
        "title" : "キースがいなくなってしまった... 中編"
      } ],
      "type" : "REGULAR"
    }, {
      "air_date" : "2021-09-11",
      "description" : "Upon learning that Keith was kidnapped, Catarina heads to the mansion that Alexander indicated to save him. The group enters the mansion even as Maria detects powerful dark magic there. After slipping past the many guards, they arrive at a hidden room, where they find Keith lying on the floor with his hands and feet bound.\nSource: crunchyroll",
      "episode_id" : 243167,
      "length" : 25,
      "number" : 11,
      "rating" : {
        "rating" : 5.12,
        "total" : 4
      },
      "recap" : false,
      "resources" : {
        "CRUNCHY_ROLL" : [ "GMKUX55K3" ]
      },
      "titles" : [ {
        "language" : "ENGLISH",
        "title" : "Keith Disappeared... Part 3"
      }, {
        "language" : "JAPANESE_TRANSLITERATED",
        "title" : "Keith ga Inakunatte Shimatta... Kouhen"
      }, {
        "language" : "FRENCH",
        "title" : "Oups, Keith a disparu… (3e partie)"
      }, {
        "language" : "ARABIC",
        "title" : "كيث اختفى... الجزء 3"
      }, {
        "language" : "JAPANESE",
        "title" : "キースがいなくなってしまった... 後編"
      } ],
      "type" : "REGULAR"
    }, {
      "air_date" : "2021-09-18",
      "description" : "Catarina Claes is finally graduating from the Magic Academy. Catarina reflects on the past two years as she talks with all of her precious friends and attends a graduation party at the castle. There, they all speak of their feelings for her, starting with Geordo.\nSource: crunchyroll",
      "episode_id" : 243168,
      "length" : 25,
      "number" : 12,
      "rating" : {
        "rating" : 4.67,
        "total" : 4
      },
      "recap" : false,
      "resources" : {
        "CRUNCHY_ROLL" : [ "GVWU0PPK0" ]
      },
      "titles" : [ {
        "language" : "FRENCH",
        "title" : "Déjà la cérémonie de remise des diplômes..."
      }, {
        "language" : "ENGLISH",
        "title" : "My Graduation Ceremony Happened..."
      }, {
        "language" : "JAPANESE_TRANSLITERATED",
        "title" : "Sotsugyoushiki ga Yatte Kite Shimatta..."
      }, {
        "language" : "JAPANESE",
        "title" : "卒業式がやって来てしまった..."
      } ],
      "type" : "REGULAR"
    } ],
    "SPECIAL" : [ {
      "air_date" : "2021-06-21",
      "episode_id" : 252874,
      "length" : 1,
      "number" : 1,
      "rating" : {
        "rating" : 2.88,
        "total" : 1
      },
      "recap" : false,
      "titles" : [ {
        "language" : "ENGLISH",
        "title" : "Catarina`s Brain Conference X 1"
      }, {
        "language" : "JAPANESE",
        "title" : "カタリナ脳内会議X #01「前世の記憶を思い出してしまった...編」"
      } ],
      "type" : "SPECIAL"
    }, {
      "air_date" : "2021-06-22",
      "episode_id" : 252875,
      "length" : 1,
      "number" : 2,
      "rating" : {
        "rating" : 1.34,
        "total" : 1
      },
      "recap" : false,
      "titles" : [ {
        "language" : "ENGLISH",
        "title" : "Catarina`s Brain Conference X 2"
      }, {
        "language" : "JAPANESE",
        "title" : "カタリナ脳内会議X #02「メアリ・アラン編」"
      } ],
      "type" : "SPECIAL"
    }, {
      "air_date" : "2021-06-23",
      "episode_id" : 252864,
      "length" : 1,
      "number" : 3,
      "rating" : {
        "rating" : 1.34,
        "total" : 1
      },
      "recap" : false,
      "titles" : [ {
        "language" : "ENGLISH",
        "title" : "Catarina`s Brain Conference X 3"
      }, {
        "language" : "JAPANESE",
        "title" : "カタリナ脳内会議X #03「ソフィア・ニコル編」"
      } ],
      "type" : "SPECIAL"
    }, {
      "air_date" : "2021-06-24",
      "episode_id" : 252865,
      "length" : 1,
      "number" : 4,
      "rating" : {
        "rating" : 1.88,
        "total" : 1
      },
      "recap" : false,
      "titles" : [ {
        "language" : "ENGLISH",
        "title" : "Catarina`s Brain Conference X 4"
      }, {
        "language" : "JAPANESE",
        "title" : "カタリナ脳内会議X #04「魔法学園入学編」"
      } ],
      "type" : "SPECIAL"
    }, {
      "air_date" : "2021-06-25",
      "episode_id" : 252866,
      "length" : 1,
      "number" : 5,
      "rating" : {
        "rating" : 1.88,
        "total" : 1
      },
      "recap" : false,
      "titles" : [ {
        "language" : "ENGLISH",
        "title" : "Catarina`s Brain Conference X 5"
      }, {
        "language" : "JAPANESE",
        "title" : "カタリナ脳内会議X #05「マリア編」"
      } ],
      "type" : "SPECIAL"
    }, {
      "air_date" : "2021-06-26",
      "episode_id" : 252867,
      "length" : 1,
      "number" : 6,
      "rating" : {
        "rating" : 1.88,
        "total" : 1
      },
      "recap" : false,
      "titles" : [ {
        "language" : "ENGLISH",
        "title" : "Catarina`s Brain Conference X 6"
      }, {
        "language" : "JAPANESE",
        "title" : "カタリナ脳内会議X #06「マリア編その2」"
      } ],
      "type" : "SPECIAL"
    }, {
      "air_date" : "2021-06-27",
      "episode_id" : 252868,
      "length" : 1,
      "number" : 7,
      "rating" : {
        "rating" : 1.34,
        "total" : 1
      },
      "recap" : false,
      "titles" : [ {
        "language" : "ENGLISH",
        "title" : "Catarina`s Brain Conference X 7"
      }, {
        "language" : "JAPANESE",
        "title" : "カタリナ脳内会議X #07「断罪イベント編」"
      } ],
      "type" : "SPECIAL"
    }, {
      "air_date" : "2021-06-28",
      "episode_id" : 252869,
      "length" : 1,
      "number" : 8,
      "rating" : {
        "rating" : 1.34,
        "total" : 1
      },
      "recap" : false,
      "titles" : [ {
        "language" : "ENGLISH",
        "title" : "Catarina`s Brain Conference X 8"
      }, {
        "language" : "JAPANESE",
        "title" : "カタリナ脳内会議X #08「闇の魔力編」"
      } ],
      "type" : "SPECIAL"
    }, {
      "air_date" : "2021-06-29",
      "episode_id" : 252870,
      "length" : 1,
      "number" : 9,
      "rating" : {
        "rating" : 1.88,
        "total" : 1
      },
      "recap" : false,
      "titles" : [ {
        "language" : "ENGLISH",
        "title" : "Catarina`s Brain Conference X 9"
      }, {
        "language" : "JAPANESE",
        "title" : "カタリナ脳内会議X #09「前世の親友編」"
      } ],
      "type" : "SPECIAL"
    }, {
      "air_date" : "2021-06-30",
      "episode_id" : 252871,
      "length" : 1,
      "number" : 10,
      "rating" : {
        "rating" : 1.88,
        "total" : 1
      },
      "recap" : false,
      "titles" : [ {
        "language" : "ENGLISH",
        "title" : "Catarina`s Brain Conference X 10"
      }, {
        "language" : "JAPANESE",
        "title" : "カタリナ脳内会議X #10「シリウス・ディーク編」"
      } ],
      "type" : "SPECIAL"
    }, {
      "air_date" : "2021-07-01",
      "episode_id" : 252872,
      "length" : 1,
      "number" : 11,
      "rating" : {
        "rating" : 2.88,
        "total" : 1
      },
      "recap" : false,
      "titles" : [ {
        "language" : "ENGLISH",
        "title" : "Catarina`s Brain Conference X 11"
      }, {
        "language" : "JAPANESE",
        "title" : "カタリナ脳内会議X #11「破滅エンド!? 編」"
      } ],
      "type" : "SPECIAL"
    }, {
      "air_date" : "2021-09-18",
      "episode_id" : 252887,
      "length" : 1,
      "number" : 12,
      "rating" : {
        "rating" : 1.88,
        "total" : 1
      },
      "recap" : false,
      "titles" : [ {
        "language" : "ENGLISH",
        "title" : "Catarina`s Brain Conference X Epilogue"
      } ],
      "type" : "SPECIAL"
    }, {
      "air_date" : "2021-12-01",
      "episode_id" : 252873,
      "length" : 4,
      "number" : 13,
      "recap" : false,
      "titles" : [ {
        "language" : "ENGLISH",
        "title" : "Eyecatch Collection"
      }, {
        "language" : "JAPANESE_TRANSLITERATED",
        "title" : "Teikyou Back Shuu"
      }, {
        "language" : "JAPANESE",
        "title" : "提供バック集"
      } ],
      "type" : "SPECIAL"
    }, {
      "air_date" : "2021-07-24",
      "episode_id" : 252827,
      "length" : 3,
      "number" : 14,
      "recap" : false,
      "titles" : [ {
        "language" : "ENGLISH",
        "title" : "Catarina Farm DX 4 Special Edition"
      }, {
        "language" : "JAPANESE_TRANSLITERATED",
        "title" : "Catarina Noujou DX #04 Tokubetsu Hen"
      }, {
        "language" : "JAPANESE",
        "title" : "カタリナ農場DX#04【特別編】"
      } ],
      "type" : "SPECIAL"
    }, {
      "air_date" : "2021-09-18",
      "episode_id" : 252826,
      "length" : 1,
      "number" : 15,
      "recap" : false,
      "titles" : [ {
        "language" : "ENGLISH",
        "title" : "Catarina Farm DX Thank You"
      }, {
        "language" : "JAPANESE_TRANSLITERATED",
        "title" : "Catarina Noujou DX Arigatou Gozaimashita"
      }, {
        "language" : "JAPANESE",
        "title" : "カタリナ農場DX \\ありがとうございました/"
      } ],
      "type" : "SPECIAL"
    } ],
    "CREDITS" : [ {
      "air_date" : "2021-07-03",
      "episode_id" : 242063,
      "length" : 2,
      "number" : 1,
      "rating" : {
        "rating" : 6.79,
        "total" : 1
      },
      "recap" : false,
      "titles" : [ {
        "language" : "ENGLISH",
        "title" : "Opening 1a"
      } ],
      "type" : "CREDITS"
    }, {
      "air_date" : "2021-08-07",
      "episode_id" : 252359,
      "length" : 2,
      "number" : 2,
      "recap" : false,
      "titles" : [ {
        "language" : "ENGLISH",
        "title" : "Opening 1b"
      } ],
      "type" : "CREDITS"
    }, {
      "air_date" : "2021-07-10",
      "episode_id" : 242064,
      "length" : 2,
      "number" : 3,
      "rating" : {
        "rating" : 2.48,
        "total" : 1
      },
      "recap" : false,
      "titles" : [ {
        "language" : "ENGLISH",
        "title" : "Ending"
      } ],
      "type" : "CREDITS"
    } ],
    "PROMOTION" : [ {
      "air_date" : "2020-06-20",
      "episode_id" : 230093,
      "length" : 1,
      "number" : 1,
      "recap" : false,
      "titles" : [ {
        "language" : "ENGLISH",
        "title" : "PV 1 (0:30) - Announcement Preview"
      }, {
        "language" : "JAPANESE",
        "title" : "【第2期決定!】「乙女ゲームの破滅フラグしかない悪役令嬢に転生してしまった...」2021年第2期制作決定PV"
      } ],
      "type" : "PROMOTION"
    }, {
      "air_date" : "2021-03-19",
      "episode_id" : 240656,
      "length" : 2,
      "number" : 2,
      "recap" : false,
      "titles" : [ {
        "language" : "JAPANESE_TRANSLITERATED",
        "title" : "Dai 1 Dan PV"
      }, {
        "language" : "ENGLISH",
        "title" : "PV 2 (1:28)"
      }, {
        "language" : "JAPANESE",
        "title" : "第1弾PV"
      } ],
      "type" : "PROMOTION"
    }, {
      "air_date" : "2021-05-28",
      "episode_id" : 240657,
      "length" : 2,
      "number" : 3,
      "recap" : false,
      "titles" : [ {
        "language" : "JAPANESE_TRANSLITERATED",
        "title" : "Dai 2 Dan PV"
      }, {
        "language" : "ENGLISH",
        "title" : "PV 3 (1:48)"
      }, {
        "language" : "JAPANESE",
        "title" : "第2弾PV"
      } ],
      "type" : "PROMOTION"
    }, {
      "air_date" : "2021-07-03",
      "episode_id" : 252876,
      "length" : 1,
      "number" : 4,
      "rating" : {
        "rating" : 1.88,
        "total" : 1
      },
      "recap" : false,
      "titles" : [ {
        "language" : "ENGLISH",
        "title" : "Episode 2 Preview"
      } ],
      "type" : "PROMOTION"
    }, {
      "air_date" : "2021-07-10",
      "episode_id" : 252877,
      "length" : 1,
      "number" : 5,
      "rating" : {
        "rating" : 1.34,
        "total" : 1
      },
      "recap" : false,
      "titles" : [ {
        "language" : "ENGLISH",
        "title" : "Episode 3 Preview"
      } ],
      "type" : "PROMOTION"
    }, {
      "air_date" : "2021-07-17",
      "episode_id" : 252878,
      "length" : 1,
      "number" : 6,
      "rating" : {
        "rating" : 1.88,
        "total" : 1
      },
      "recap" : false,
      "titles" : [ {
        "language" : "ENGLISH",
        "title" : "Episode 4 Preview"
      } ],
      "type" : "PROMOTION"
    }, {
      "air_date" : "2021-07-24",
      "episode_id" : 252879,
      "length" : 1,
      "number" : 7,
      "rating" : {
        "rating" : 1.34,
        "total" : 1
      },
      "recap" : false,
      "titles" : [ {
        "language" : "ENGLISH",
        "title" : "Episode 5 Preview"
      } ],
      "type" : "PROMOTION"
    }, {
      "air_date" : "2021-07-31",
      "episode_id" : 252880,
      "length" : 1,
      "number" : 8,
      "rating" : {
        "rating" : 1.34,
        "total" : 1
      },
      "recap" : false,
      "titles" : [ {
        "language" : "ENGLISH",
        "title" : "Episode 6 Preview"
      } ],
      "type" : "PROMOTION"
    }, {
      "air_date" : "2021-08-07",
      "episode_id" : 252881,
      "length" : 1,
      "number" : 9,
      "rating" : {
        "rating" : 1.34,
        "total" : 1
      },
      "recap" : false,
      "titles" : [ {
        "language" : "ENGLISH",
        "title" : "Episode 7 Preview"
      } ],
      "type" : "PROMOTION"
    }, {
      "air_date" : "2021-08-14",
      "episode_id" : 252882,
      "length" : 1,
      "number" : 10,
      "rating" : {
        "rating" : 1.34,
        "total" : 1
      },
      "recap" : false,
      "titles" : [ {
        "language" : "ENGLISH",
        "title" : "Episode 8 Preview"
      } ],
      "type" : "PROMOTION"
    }, {
      "air_date" : "2021-08-21",
      "episode_id" : 252883,
      "length" : 1,
      "number" : 11,
      "rating" : {
        "rating" : 1.88,
        "total" : 1
      },
      "recap" : false,
      "titles" : [ {
        "language" : "ENGLISH",
        "title" : "Episode 9 Preview"
      } ],
      "type" : "PROMOTION"
    }, {
      "air_date" : "2021-08-28",
      "episode_id" : 252884,
      "length" : 1,
      "number" : 12,
      "rating" : {
        "rating" : 1.34,
        "total" : 1
      },
      "recap" : false,
      "titles" : [ {
        "language" : "ENGLISH",
        "title" : "Episode 10 Preview"
      } ],
      "type" : "PROMOTION"
    }, {
      "air_date" : "2021-09-04",
      "episode_id" : 252885,
      "length" : 1,
      "number" : 13,
      "rating" : {
        "rating" : 1.34,
        "total" : 1
      },
      "recap" : false,
      "titles" : [ {
        "language" : "ENGLISH",
        "title" : "Episode 11 Preview"
      } ],
      "type" : "PROMOTION"
    }, {
      "air_date" : "2021-09-11",
      "episode_id" : 252886,
      "length" : 1,
      "number" : 14,
      "rating" : {
        "rating" : 1.34,
        "total" : 1
      },
      "recap" : false,
      "titles" : [ {
        "language" : "ENGLISH",
        "title" : "Episode 12 Preview"
      } ],
      "type" : "PROMOTION"
    }, {
      "air_date" : "2021-07-01",
      "episode_id" : 252815,
      "length" : 1,
      "number" : 15,
      "recap" : false,
      "titles" : [ {
        "language" : "ENGLISH",
        "title" : "Catarina Farm DX Preview (0:51)"
      }, {
        "language" : "JAPANESE_TRANSLITERATED",
        "title" : "Catarina Noujou DX Yokoku Douga"
      }, {
        "language" : "JAPANESE",
        "title" : "カタリナ農場DX予告動画"
      } ],
      "type" : "PROMOTION"
    }, {
      "air_date" : "2021-07-01",
      "episode_id" : 252816,
      "length" : 1,
      "number" : 16,
      "recap" : false,
      "titles" : [ {
        "language" : "ENGLISH",
        "title" : "Catarina Farm DX 1 (0:30)"
      }, {
        "language" : "JAPANESE_TRANSLITERATED",
        "title" : "Catarina Noujou DX #01"
      }, {
        "language" : "JAPANESE",
        "title" : "カタリナ農場DX#01"
      } ],
      "type" : "PROMOTION"
    }, {
      "air_date" : "2021-07-10",
      "episode_id" : 252817,
      "length" : 1,
      "number" : 17,
      "recap" : false,
      "titles" : [ {
        "language" : "ENGLISH",
        "title" : "Catarina Farm DX 2 (0:30)"
      }, {
        "language" : "JAPANESE_TRANSLITERATED",
        "title" : "Catarina Noujou DX #02"
      }, {
        "language" : "JAPANESE",
        "title" : "カタリナ農場DX#02"
      } ],
      "type" : "PROMOTION"
    }, {
      "air_date" : "2021-07-17",
      "episode_id" : 252818,
      "length" : 1,
      "number" : 18,
      "recap" : false,
      "titles" : [ {
        "language" : "ENGLISH",
        "title" : "Catarina Farm DX 3 (0:30)"
      }, {
        "language" : "JAPANESE_TRANSLITERATED",
        "title" : "Catarina Noujou DX #03"
      }, {
        "language" : "JAPANESE",
        "title" : "カタリナ農場DX#03"
      } ],
      "type" : "PROMOTION"
    }, {
      "air_date" : "2021-07-24",
      "episode_id" : 252819,
      "length" : 1,
      "number" : 19,
      "recap" : false,
      "titles" : [ {
        "language" : "ENGLISH",
        "title" : "Catarina Farm DX 4 (0:30)"
      }, {
        "language" : "JAPANESE_TRANSLITERATED",
        "title" : "Catarina Noujou DX #04"
      }, {
        "language" : "JAPANESE",
        "title" : "カタリナ農場DX#04"
      } ],
      "type" : "PROMOTION"
    }, {
      "air_date" : "2021-07-31",
      "episode_id" : 252820,
      "length" : 1,
      "number" : 20,
      "recap" : false,
      "titles" : [ {
        "language" : "ENGLISH",
        "title" : "Catarina Farm DX 5 (0:30)"
      }, {
        "language" : "JAPANESE_TRANSLITERATED",
        "title" : "Catarina Noujou DX #05"
      }, {
        "language" : "JAPANESE",
        "title" : "カタリナ農場DX#05"
      } ],
      "type" : "PROMOTION"
    }, {
      "air_date" : "2021-08-07",
      "episode_id" : 252821,
      "length" : 1,
      "number" : 21,
      "recap" : false,
      "titles" : [ {
        "language" : "ENGLISH",
        "title" : "Catarina Farm DX 6 (0:30)"
      }, {
        "language" : "JAPANESE_TRANSLITERATED",
        "title" : "Catarina Noujou DX #06"
      }, {
        "language" : "JAPANESE",
        "title" : "カタリナ農場DX#06"
      } ],
      "type" : "PROMOTION"
    }, {
      "air_date" : "2021-08-14",
      "episode_id" : 252822,
      "length" : 1,
      "number" : 22,
      "recap" : false,
      "titles" : [ {
        "language" : "ENGLISH",
        "title" : "Catarina Farm DX 7 (0:30)"
      }, {
        "language" : "JAPANESE_TRANSLITERATED",
        "title" : "Catarina Noujou DX #07"
      }, {
        "language" : "JAPANESE",
        "title" : "カタリナ農場DX#07"
      } ],
      "type" : "PROMOTION"
    }, {
      "air_date" : "2021-08-21",
      "episode_id" : 252823,
      "length" : 1,
      "number" : 23,
      "recap" : false,
      "titles" : [ {
        "language" : "ENGLISH",
        "title" : "Catarina Farm DX 8 (0:30)"
      }, {
        "language" : "JAPANESE_TRANSLITERATED",
        "title" : "Catarina Noujou DX #08"
      }, {
        "language" : "JAPANESE",
        "title" : "カタリナ農場DX#08"
      } ],
      "type" : "PROMOTION"
    }, {
      "air_date" : "2021-08-28",
      "episode_id" : 252824,
      "length" : 1,
      "number" : 24,
      "recap" : false,
      "titles" : [ {
        "language" : "ENGLISH",
        "title" : "Catarina Farm DX 9 (0:30)"
      }, {
        "language" : "JAPANESE_TRANSLITERATED",
        "title" : "Catarina Noujou DX #09"
      }, {
        "language" : "JAPANESE",
        "title" : "カタリナ農場DX#09"
      } ],
      "type" : "PROMOTION"
    }, {
      "air_date" : "2021-09-04",
      "episode_id" : 252825,
      "length" : 1,
      "number" : 25,
      "recap" : false,
      "titles" : [ {
        "language" : "ENGLISH",
        "title" : "Catarina Farm DX 10 (0:30)"
      }, {
        "language" : "JAPANESE_TRANSLITERATED",
        "title" : "Catarina Noujou DX #10"
      }, {
        "language" : "JAPANESE",
        "title" : "カタリナ農場DX#10"
      } ],
      "type" : "PROMOTION"
    }, {
      "air_date" : "2021-09-11",
      "episode_id" : 252828,
      "length" : 1,
      "number" : 26,
      "recap" : false,
      "titles" : [ {
        "language" : "ENGLISH",
        "title" : "Catarina Farm DX 11 (0:30)"
      }, {
        "language" : "JAPANESE_TRANSLITERATED",
        "title" : "Catarina Noujou DX #11"
      }, {
        "language" : "JAPANESE",
        "title" : "カタリナ農場DX#11"
      } ],
      "type" : "PROMOTION"
    } ]
  },
  "ratings" : {
    "PERMANENT" : {
      "rating" : 5.44,
      "total" : 787
    },
    "TEMPORARY" : {
      "rating" : 6.73,
      "total" : 794
    }
  },
  "related" : {
    "OTHER" : [ 16727 ],
    "PREQUEL" : [ 14449 ]
  },
  "resources" : {
    "ALL_CINEMA" : [ "373026" ],
    "ANISON" : [ "23428" ],
    "ANN" : [ "23895" ],
    "CRUNCHY_ROLL" : [ "GY5PW4JEY" ],
    "MAL" : [ "42282" ],
    "SYOBOI" : [ "6035" ],
    "TWITTER" : [ "hamehura", "hamehura/status/1406944992644374537", "hamehura/status/1407292282261233669", "hamehura/status/1407655171115536384", "hamehura/status/1408017059473235969", "hamehura/status/1408379450362847233", "hamehura/status/1408741837720883206", "hamehura/status/1409104222998564871", "hamehura/status/1409492286371549188", "hamehura/status/1409829004283060225", "hamehura/status/1410191391054041094", "hamehura/status/1410553780182163456", "hamehura/status/1411005496450904071", "hamehura/status/1413545368348889096", "hamehura/status/1416078675011903493", "hamehura/status/1418617906959732741", "hamehura/status/1421160661330104321", "hamehura/status/1423696585070845961", "hamehura/status/1426225535277993992", "hamehura/status/1428762250177777668", "hamehura/status/1431300223666638858", "hamehura/status/1433836938524459009", "hamehura/status/1436372395313582090", "hamehura/status/1438909471573479429" ],
    "WEBSITE" : [ "https://hamehura-anime.com/" ],
    "WIKIPEDIA_EN" : [ "My_Next_Life_as_a_Villainess:_All_Routes_Lead_to_Doom!" ],
    "WIKIPEDIA_JP" : [ "乙女ゲームの破滅フラグしかない悪役令嬢に転生してしまった…" ],
    "YOUTUBE" : [ "watch?v=8ZKS83C6kbw", "watch?v=B_lA8U62cJI", "watch?v=EfW16pAsyz4", "watch?v=QAd-jpLqKOc", "watch?v=U89R_rcrbUs", "watch?v=VJGpWcF9N9E", "watch?v=XXwQ9pBt21Q", "watch?v=apvVH0Xe4yI", "watch?v=broSl96yJP0", "watch?v=eiOfyu8O8kc", "watch?v=ffnihDg-2hs", "watch?v=jj0WfDp8pfs", "watch?v=kW1l2vk_PRk", "watch?v=pUi-KEhp4C8", "watch?v=rbZVRTUymGc", "watch?v=tiJBMTOabzg", "watch?v=yHfyk8iqcPk" ]
  },
  "start_date" : "2021-07-03",
  "tags" : {
    "780" : {
      "info_box" : false,
      "name" : "fairy",
      "parent_tag_id" : 2849,
      "spoiler" : false,
      "verified" : false,
      "weight" : 100
    },
    "1077" : {
      "info_box" : true,
      "name" : "shoujo",
      "parent_tag_id" : 2606,
      "spoiler" : false,
      "verified" : false,
      "weight" : 0
    },
    "1157" : {
      "info_box" : false,
      "name" : "horny nosebleed",
      "parent_tag_id" : 2653,
      "spoiler" : false,
      "verified" : false,
      "weight" : 0
    },
    "2072" : {
      "info_box" : true,
      "name" : "maid",
      "parent_tag_id" : 2608,
      "spoiler" : false,
      "verified" : false,
      "weight" : 400
    },
    "2094" : {
      "info_box" : false,
      "name" : "magic",
      "parent_tag_id" : 2849,
      "spoiler" : false,
      "verified" : false,
      "weight" : 100
    },
    "2355" : {
      "info_box" : false,
      "name" : "dragon",
      "parent_tag_id" : 2849,
      "spoiler" : false,
      "verified" : false,
      "weight" : 100
    },
    "2604" : {
      "info_box" : false,
      "name" : "content indicators",
      "spoiler" : false,
      "verified" : false,
      "weight" : 0
    },
    "2605" : {
      "info_box" : false,
      "name" : "dynamic",
      "spoiler" : false,
      "verified" : false,
      "weight" : 0
    },
    "2606" : {
      "info_box" : false,
      "name" : "target audience",
      "spoiler" : false,
      "verified" : false,
      "weight" : 0
    },
    "2607" : {
      "info_box" : false,
      "name" : "themes",
      "spoiler" : false,
      "verified" : false,
      "weight" : 0
    },
    "2608" : {
      "info_box" : false,
      "name" : "fetishes",
      "spoiler" : false,
      "verified" : false,
      "weight" : 0
    },
    "2609" : {
      "info_box" : false,
      "name" : "original work",
      "spoiler" : false,
      "verified" : false,
      "weight" : 0
    },
    "2610" : {
      "info_box" : false,
      "name" : "setting",
      "spoiler" : false,
      "verified" : false,
      "weight" : 0
    },
    "2611" : {
      "info_box" : false,
      "name" : "elements",
      "spoiler" : false,
      "verified" : false,
      "weight" : 0
    },
    "2613" : {
      "info_box" : false,
      "name" : "place",
      "parent_tag_id" : 2610,
      "spoiler" : false,
      "verified" : false,
      "weight" : 0
    },
    "2614" : {
      "info_box" : true,
      "name" : "josei",
      "parent_tag_id" : 2606,
      "spoiler" : false,
      "verified" : false,
      "weight" : 0
    },
    "2622" : {
      "info_box" : false,
      "name" : "swordplay",
      "parent_tag_id" : 2841,
      "spoiler" : false,
      "verified" : false,
      "weight" : 100
    },
    "2628" : {
      "info_box" : false,
      "name" : "fictional location",
      "parent_tag_id" : 2613,
      "spoiler" : false,
      "verified" : false,
      "weight" : 500
    },
    "2653" : {
      "info_box" : false,
      "name" : "slapstick",
      "parent_tag_id" : 2853,
      "spoiler" : false,
      "verified" : false,
      "weight" : 100
    },
    "2655" : {
      "info_box" : false,
      "name" : "parody",
      "parent_tag_id" : 2853,
      "spoiler" : false,
      "verified" : false,
      "weight" : 100
    },
    "2750" : {
      "info_box" : false,
      "name" : "violence",
      "parent_tag_id" : 2604,
      "spoiler" : false,
      "verified" : false,
      "weight" : 100
    },
    "2782" : {
      "info_box" : false,
      "name" : "shoujo ai",
      "parent_tag_id" : 2858,
      "spoiler" : false,
      "verified" : false,
      "weight" : 100
    },
    "2785" : {
      "info_box" : false,
      "name" : "unrequited love",
      "parent_tag_id" : 2858,
      "spoiler" : false,
      "verified" : false,
      "weight" : 100
    },
    "2792" : {
      "info_box" : false,
      "name" : "reverse harem",
      "parent_tag_id" : 2611,
      "spoiler" : false,
      "verified" : false,
      "weight" : 300
    },
    "2799" : {
      "info_box" : true,
      "name" : "novel",
      "parent_tag_id" : 2609,
      "spoiler" : false,
      "verified" : false,
      "weight" : 0
    },
    "2841" : {
      "info_box" : false,
      "name" : "action",
      "parent_tag_id" : 2611,
      "spoiler" : false,
      "verified" : false,
      "weight" : 0
    },
    "2849" : {
      "info_box" : true,
      "name" : "fantasy",
      "parent_tag_id" : 7050,
      "spoiler" : false,
      "verified" : false,
      "weight" : 500
    },
    "2853" : {
      "info_box" : false,
      "name" : "comedy",
      "parent_tag_id" : 2611,
      "spoiler" : false,
      "verified" : false,
      "weight" : 300
    },
    "2858" : {
      "info_box" : false,
      "name" : "romance",
      "parent_tag_id" : 2611,
      "spoiler" : false,
      "verified" : false,
      "weight" : 100
    },
    "2859" : {
      "info_box" : false,
      "name" : "harem",
      "parent_tag_id" : 2611,
      "spoiler" : false,
      "verified" : false,
      "weight" : 200
    },
    "2862" : {
      "info_box" : false,
      "name" : "friendship",
      "parent_tag_id" : 2607,
      "spoiler" : false,
      "verified" : false,
      "weight" : 400
    },
    "2869" : {
      "info_box" : false,
      "name" : "school life",
      "parent_tag_id" : 2607,
      "spoiler" : false,
      "verified" : false,
      "weight" : 100
    },
    "2888" : {
      "info_box" : false,
      "name" : "coming of age",
      "parent_tag_id" : 2607,
      "spoiler" : false,
      "verified" : false,
      "weight" : 200
    },
    "2931" : {
      "info_box" : false,
      "name" : "unsorted",
      "spoiler" : false,
      "verified" : false,
      "weight" : 0
    },
    "3023" : {
      "info_box" : false,
      "name" : "funny expressions",
      "parent_tag_id" : 2853,
      "spoiler" : false,
      "verified" : false,
      "weight" : 0
    },
    "3508" : {
      "info_box" : false,
      "name" : "school for the rich elite",
      "parent_tag_id" : 2869,
      "spoiler" : false,
      "verified" : false,
      "weight" : 0
    },
    "3683" : {
      "info_box" : false,
      "name" : "storytelling",
      "parent_tag_id" : 2605,
      "spoiler" : false,
      "verified" : false,
      "weight" : 0
    },
    "3751" : {
      "info_box" : false,
      "name" : "grandiose displays of wealth",
      "parent_tag_id" : 6243,
      "spoiler" : false,
      "verified" : false,
      "weight" : 0
    },
    "3805" : {
      "info_box" : false,
      "name" : "European stylised",
      "parent_tag_id" : 2611,
      "spoiler" : false,
      "verified" : false,
      "weight" : 0
    },
    "3977" : {
      "info_box" : false,
      "name" : "dialogue driven",
      "parent_tag_id" : 3683,
      "spoiler" : false,
      "verified" : false,
      "weight" : 0
    },
    "4022" : {
      "info_box" : false,
      "name" : "strong female lead",
      "parent_tag_id" : 6230,
      "spoiler" : false,
      "verified" : false,
      "weight" : 0
    },
    "4030" : {
      "info_box" : false,
      "name" : "mental cinema",
      "parent_tag_id" : 2931,
      "spoiler" : false,
      "verified" : false,
      "weight" : 0
    },
    "5543" : {
      "info_box" : false,
      "name" : "magic school",
      "parent_tag_id" : 2094,
      "spoiler" : false,
      "verified" : false,
      "weight" : 0
    },
    "5794" : {
      "info_box" : false,
      "name" : "forbidden love",
      "parent_tag_id" : 2858,
      "spoiler" : false,
      "verified" : false,
      "weight" : 0
    },
    "5851" : {
      "info_box" : false,
      "name" : "female protagonist",
      "parent_tag_id" : 6230,
      "spoiler" : false,
      "verified" : false,
      "weight" : 0
    },
    "5973" : {
      "info_box" : false,
      "name" : "agriculture",
      "parent_tag_id" : 2607,
      "spoiler" : false,
      "verified" : false,
      "weight" : 0
    },
    "6021" : {
      "info_box" : false,
      "name" : "gender bender",
      "parent_tag_id" : 2611,
      "spoiler" : false,
      "verified" : false,
      "weight" : 0
    },
    "6088" : {
      "info_box" : false,
      "name" : "unrequited shoujo ai",
      "parent_tag_id" : 2785,
      "spoiler" : false,
      "verified" : false,
      "weight" : 0
    },
    "6173" : {
      "info_box" : false,
      "name" : "origin",
      "spoiler" : false,
      "verified" : false,
      "weight" : 0
    },
    "6230" : {
      "info_box" : false,
      "name" : "cast",
      "parent_tag_id" : 2605,
      "spoiler" : false,
      "verified" : false,
      "weight" : 0
    },
    "6243" : {
      "info_box" : false,
      "name" : "money",
      "parent_tag_id" : 2607,
      "spoiler" : false,
      "verified" : false,
      "weight" : 0
    },
    "6744" : {
      "info_box" : true,
      "name" : "isekai",
      "parent_tag_id" : 2607,
      "spoiler" : false,
      "verified" : false,
      "weight" : 0
    },
    "7050" : {
      "info_box" : false,
      "name" : "speculative fiction",
      "parent_tag_id" : 2611,
      "spoiler" : false,
      "verified" : false,
      "weight" : 0
    },
    "7885" : {
      "info_box" : false,
      "name" : "Japanese production",
      "parent_tag_id" : 6173,
      "spoiler" : false,
      "verified" : false,
      "weight" : 0
    }
  },
  "titles" : [ {
    "language" : "JAPANESE_TRANSLITERATED",
    "title" : "Otome Game no Hametsu Flag shika Nai Akuyaku Reijou ni Tensei Shiteshimatta... X",
    "type" : "MAIN"
  }, {
    "language" : "ENGLISH",
    "title" : "My Next Life as a Villainess: All Routes Lead to Doom! X",
    "type" : "OFFICIAL"
  }, {
    "language" : "RUSSIAN",
    "title" : "Моя реинкарнация в отомэ-игре в качестве главной злодейки X",
    "type" : "OFFICIAL"
  }, {
    "language" : "JAPANESE",
    "title" : "乙女ゲームの破滅フラグしかない悪役令嬢に転生してしまった...X",
    "type" : "OFFICIAL"
  }, {
    "language" : "CHINESE_SIMPLIFIED",
    "title" : "转生成为了只有乙女游戏破灭结局的邪恶大小姐 X",
    "type" : "OFFICIAL"
  }, {
    "language" : "KOREAN",
    "title" : "여성향 게임의 파멸 플래그밖에 없는 악역 영애로 환생해버렸다...X",
    "type" : "OFFICIAL"
  }, {
    "language" : "ENGLISH",
    "title" : "Bakarina 2",
    "type" : "SHORT"
  }, {
    "language" : "JAPANESE_TRANSLITERATED",
    "title" : "Hamefura 2",
    "type" : "SHORT"
  }, {
    "language" : "JAPANESE_TRANSLITERATED",
    "title" : "hamefura s2",
    "type" : "SHORT"
  }, {
    "language" : "JAPANESE_TRANSLITERATED",
    "title" : "hamefurax",
    "type" : "SHORT"
  }, {
    "language" : "JAPANESE",
    "title" : "はめふら 2",
    "type" : "SHORT"
  }, {
    "language" : "RUSSIAN",
    "title" : "Моя реинкарнация в отомэ-игре в роли главной злодейки 2",
    "type" : "SYNONYM"
  } ],
  "type" : "SERIES",
  "url" : "https://hamehura-anime.com/"
}