{
  "anime_id" : 19181,
  "creators" : {
    "1163" : [ {
      "name" : "SynergySP",
      "type" : "ANIMATION_WORK"
    } ],
    "2754" : [ {
      "name" : "Takanashi Yasuharu",
      "type" : "MUSIC"
    } ],
    "80321" : [ {
      "name" : "Imamura Shougo",
      "type" : "ORIGINAL_WORK"
    } ],
    "84189" : [ {
      "name" : "Mori Ryuusuke",
      "type" : "SERIES_COMPOSITION"
    } ]
  },
  "episodes" : {
    "REGULAR" : [ {
      "air_date" : "2026-01-11",
      "episode_id" : 305908,
      "length" : 25,
      "number" : 1,
      "recap" : false,
      "titles" : [ {
        "language" : "ENGLISH",
        "title" : "Episode 1"
      }, {
        "language" : "JAPANESE_TRANSLITERATED",
        "title" : "Saisei no Hidane"
      }, {
        "language" : "JAPANESE",
        "title" : "再生の火種"
      } ],
      "type" : "REGULAR"
    }, {
      "air_date" : "2026-01-18",
      "episode_id" : 305909,
      "length" : 25,
      "number" : 2,
      "recap" : false,
      "titles" : [ {
        "language" : "ENGLISH",
        "title" : "Episode 2"
      } ],
      "type" : "REGULAR"
    }, {
      "air_date" : "2026-01-25",
      "episode_id" : 305910,
      "length" : 25,
      "number" : 3,
      "recap" : false,
      "titles" : [ {
        "language" : "ENGLISH",
        "title" : "Episode 3"
      } ],
      "type" : "REGULAR"
    }, {
      "air_date" : "2026-02-01",
      "episode_id" : 305911,
      "length" : 25,
      "number" : 4,
      "recap" : false,
      "titles" : [ {
        "language" : "ENGLISH",
        "title" : "Episode 4"
      } ],
      "type" : "REGULAR"
    } ]
  },
  "resources" : {
    "ALL_CINEMA" : [ "401999" ],
    "ANN" : [ "34843" ],
    "MAL" : [ "61084" ],
    "SYOBOI" : [ "7672" ],
    "TWITTER" : [ "hikuidori_pj" ],
    "WEBSITE" : [ "https://hikuidori-project.com/" ],
    "WIKIPEDIA_EN" : [ "Ushūboro_Tobigumi" ],
    "WIKIPEDIA_JP" : [ "羽州ぼろ鳶組シリーズ" ]
  },
  "start_date" : "2026-01-11",
  "tags" : {
    "6173" : {
      "info_box" : false,
      "name" : "origin",
      "spoiler" : false,
      "verified" : false,
      "weight" : 0
    },
    "7885" : {
      "info_box" : false,
      "name" : "Japanese production",
      "parent_tag_id" : 6173,
      "spoiler" : false,
      "verified" : false,
      "weight" : 0
    }
  },
  "titles" : [ {
    "language" : "JAPANESE_TRANSLITERATED",
    "title" : "Hikuidori: Ushuu Boro Tobi-gumi",
    "type" : "MAIN"
  }, {
    "language" : "JAPANESE",
    "title" : "火喰鳥 羽州ぼろ鳶組",
    "type" : "OFFICIAL"
  }, {
    "language" : "ENGLISH",
    "title" : "Oedo Fire Slayer -The Legend of Phoenix-",
    "type" : "SYNONYM"
  } ],
  "type" : "SERIES",
  "url" : "https://hikuidori-project.com/"
}