{
  "anime_id" : 4628,
  "creators" : {
    "2241" : [ {
      "name" : "Nishimura Junji",
      "type" : "CHIEF_DIRECTOR"
    } ],
    "4444" : [ {
      "name" : "Tsutsui Hiroshi",
      "type" : "MUSIC"
    } ],
    "6394" : [ {
      "name" : "Matsuoka Seiji",
      "type" : "SERIES_COMPOSITION"
    } ]
  },
  "end_date" : "1988-06-13",
  "episodes" : {
    "REGULAR" : [ {
      "air_date" : "1988-04-11",
      "episode_id" : 56040,
      "length" : 20,
      "number" : 1,
      "recap" : false,
      "titles" : [ {
        "language" : "ENGLISH",
        "title" : "Episode 1"
      }, {
        "language" : "JAPANESE",
        "title" : "ゴルフ場は大混乱"
      } ],
      "type" : "REGULAR"
    }, {
      "air_date" : "1988-04-18",
      "episode_id" : 56041,
      "length" : 20,
      "number" : 2,
      "recap" : false,
      "titles" : [ {
        "language" : "ENGLISH",
        "title" : "Episode 2"
      }, {
        "language" : "JAPANESE",
        "title" : "三人のパットメン"
      } ],
      "type" : "REGULAR"
    }, {
      "air_date" : "1988-04-25",
      "episode_id" : 56042,
      "length" : 20,
      "number" : 3,
      "recap" : false,
      "titles" : [ {
        "language" : "ENGLISH",
        "title" : "Episode 3"
      }, {
        "language" : "JAPANESE",
        "title" : "若葉ちゃんと勝負"
      } ],
      "type" : "REGULAR"
    }, {
      "air_date" : "1988-05-02",
      "episode_id" : 56043,
      "length" : 20,
      "number" : 4,
      "recap" : false,
      "titles" : [ {
        "language" : "ENGLISH",
        "title" : "Episode 4"
      }, {
        "language" : "JAPANESE",
        "title" : "あの鯉のぼりを撃て!"
      } ],
      "type" : "REGULAR"
    }, {
      "air_date" : "1988-05-09",
      "episode_id" : 56044,
      "length" : 20,
      "number" : 5,
      "recap" : false,
      "titles" : [ {
        "language" : "ENGLISH",
        "title" : "Episode 5"
      }, {
        "language" : "JAPANESE",
        "title" : "魔のパター"
      } ],
      "type" : "REGULAR"
    }, {
      "air_date" : "1988-05-16",
      "episode_id" : 56045,
      "length" : 20,
      "number" : 6,
      "recap" : false,
      "titles" : [ {
        "language" : "ENGLISH",
        "title" : "Episode 6"
      }, {
        "language" : "JAPANESE",
        "title" : "猿谷のユーレイ"
      } ],
      "type" : "REGULAR"
    }, {
      "air_date" : "1988-05-23",
      "episode_id" : 56046,
      "length" : 20,
      "number" : 7,
      "recap" : false,
      "titles" : [ {
        "language" : "ENGLISH",
        "title" : "Episode 7"
      }, {
        "language" : "JAPANESE",
        "title" : "ゴエモン, パットする"
      } ],
      "type" : "REGULAR"
    }, {
      "air_date" : "1988-05-30",
      "episode_id" : 56047,
      "length" : 20,
      "number" : 8,
      "recap" : false,
      "titles" : [ {
        "language" : "ENGLISH",
        "title" : "Episode 8"
      }, {
        "language" : "JAPANESE",
        "title" : "黒いセールスマン"
      } ],
      "type" : "REGULAR"
    }, {
      "air_date" : "1988-06-06",
      "episode_id" : 56048,
      "length" : 20,
      "number" : 9,
      "recap" : false,
      "titles" : [ {
        "language" : "ENGLISH",
        "title" : "Episode 9"
      }, {
        "language" : "JAPANESE",
        "title" : "ゴルフ天狗"
      } ],
      "type" : "REGULAR"
    }, {
      "air_date" : "1988-06-13",
      "episode_id" : 56049,
      "length" : 20,
      "number" : 10,
      "recap" : false,
      "titles" : [ {
        "language" : "ENGLISH",
        "title" : "Episode 10"
      }, {
        "language" : "JAPANESE",
        "title" : "芝ドロボーを探せ!"
      } ],
      "type" : "REGULAR"
    } ]
  },
  "ratings" : {
    "PERMANENT" : {
      "rating" : 3.69,
      "total" : 11
    },
    "TEMPORARY" : {
      "rating" : 4.18,
      "total" : 11
    }
  },
  "related" : {
    "PREQUEL" : [ 3167 ]
  },
  "resources" : {
    "ALL_CINEMA" : [ "235422" ],
    "ANISON" : [ "633" ],
    "MAL" : [ "17315" ],
    "WIKIPEDIA_JP" : [ "プロゴルファー猿" ]
  },
  "start_date" : "1988-04-11",
  "tags" : {
    "2607" : {
      "info_box" : false,
      "name" : "themes",
      "spoiler" : false,
      "verified" : false,
      "weight" : 0
    },
    "2762" : {
      "info_box" : true,
      "name" : "golf",
      "parent_tag_id" : 2881,
      "spoiler" : false,
      "verified" : false,
      "weight" : 400
    },
    "2881" : {
      "info_box" : true,
      "name" : "sports",
      "parent_tag_id" : 2607,
      "spoiler" : false,
      "verified" : false,
      "weight" : 400
    },
    "6173" : {
      "info_box" : false,
      "name" : "origin",
      "spoiler" : false,
      "verified" : false,
      "weight" : 0
    },
    "7885" : {
      "info_box" : false,
      "name" : "Japanese production",
      "parent_tag_id" : 6173,
      "spoiler" : false,
      "verified" : false,
      "weight" : 0
    }
  },
  "titles" : [ {
    "language" : "JAPANESE_TRANSLITERATED",
    "title" : "Shin Pro Golfer Saru",
    "type" : "MAIN"
  }, {
    "language" : "JAPANESE",
    "title" : "新プロゴルファー猿",
    "type" : "OFFICIAL"
  } ],
  "type" : "SERIES"
}