{
  "air_date" : "2012-05-04",
  "anime_id" : 8848,
  "description" : "Samurais are gaining popularity over Japan.  A documentary crew is interviewing some of them including Bokuden-chan, the strongest swordsman, but when the film comes out.  The Samurai Girls have a new problem to deal with.\nSource: crunchyroll",
  "episode_id" : 139174,
  "length" : 25,
  "number" : 5,
  "rating" : {
    "rating" : 3.28,
    "total" : 1
  },
  "recap" : false,
  "resources" : {
    "CRUNCHY_ROLL" : [ "GY0971E0Y" ]
  },
  "titles" : [ {
    "language" : "ENGLISH",
    "title" : "Sword Maiden"
  }, {
    "language" : "JAPANESE",
    "title" : "Sword Maiden"
  }, {
    "language" : "JAPANESE_TRANSLITERATED",
    "title" : "Sword Maiden"
  } ],
  "type" : "REGULAR"
}