{
  "air_date" : "2016-03-31",
  "anime_id" : 11500,
  "description" : "Enigma storms the Alayashiki research facility.\nSource: crunchyroll",
  "episode_id" : 176014,
  "length" : 25,
  "number" : 13,
  "rating" : {
    "rating" : 6.96,
    "total" : 11
  },
  "recap" : false,
  "resources" : {
    "CRUNCHY_ROLL" : [ "G6X03W70Y" ]
  },
  "titles" : [ {
    "language" : "JAPANESE_TRANSLITERATED",
    "title" : "Eien no Phantom World"
  }, {
    "language" : "ENGLISH",
    "title" : "The Eternal Phantom World"
  }, {
    "language" : "FRENCH",
    "title" : "Un monde de Phantoms éternel"
  }, {
    "language" : "JAPANESE",
    "title" : "永遠のファントム・ワールド"
  } ],
  "type" : "REGULAR"
}