{
  "air_date" : "2017-01-22",
  "anime_id" : 12103,
  "episode_id" : 183095,
  "length" : 15,
  "number" : 16,
  "recap" : false,
  "titles" : [ {
    "language" : "TURKISH",
    "title" : "Chi Babasının İşine Yardım Eder"
  }, {
    "language" : "ENGLISH",
    "title" : "Chi Helps Daddy Work"
  }, {
    "language" : "FRENCH",
    "title" : "Chi met la main à la \"patte\""
  }, {
    "language" : "JAPANESE_TRANSLITERATED",
    "title" : "Chii, Oshigoto Suru"
  }, {
    "language" : "JAPANESE",
    "title" : "チー, お仕事する"
  } ],
  "type" : "REGULAR"
}