{
  "air_date" : "2017-07-22",
  "anime_id" : 12132,
  "description" : "Rei has found a clue about Hajime`s whereabouts. Though Eri is thinking of quitting Appliyama because of L-Corp`s new CEO, he gets her to agree to let him disguise as her manager to infiltrate the company. But what is his plan?!\nSource: crunchyroll",
  "episode_id" : 188931,
  "length" : 25,
  "number" : 42,
  "rating" : {
    "rating" : 6.92,
    "total" : 1
  },
  "recap" : false,
  "resources" : {
    "CRUNCHY_ROLL" : [ "GREXDQK3Y" ]
  },
  "titles" : [ {
    "language" : "JAPANESE_TRANSLITERATED",
    "title" : "Rei no Ketsui! Hajime Sousaku Daisakusen!"
  }, {
    "language" : "ENGLISH",
    "title" : "Rei`s Determination! The Plan to Take Back Hajime!"
  }, {
    "language" : "JAPANESE",
    "title" : "レイの決意! はじめ捜索大作戦!"
  } ],
  "type" : "REGULAR"
}