{
  "air_date" : "2019-01-22",
  "anime_id" : 13839,
  "description" : "Sales are down, so the employees must come up with a special event. But more importantly, the world of “The Rosy Maidens” has fallen victim to the virus!\nSource: crunchyroll",
  "episode_id" : 211128,
  "length" : 25,
  "number" : 3,
  "rating" : {
    "rating" : 1.35,
    "total" : 2
  },
  "recap" : false,
  "resources" : {
    "CRUNCHY_ROLL" : [ "GYXJDZ8P6" ]
  },
  "titles" : [ {
    "language" : "JAPANESE_TRANSLITERATED",
    "title" : "Barairo no Otome, na no"
  }, {
    "language" : "FRENCH",
    "title" : "La poupée aux roses"
  }, {
    "language" : "ENGLISH",
    "title" : "We`re the Rosy Maidens"
  }, {
    "language" : "JAPANESE",
    "title" : "薔薇色の乙女, なの"
  } ],
  "type" : "REGULAR"
}