{
  "air_date" : "2020-07-07",
  "anime_id" : 14537,
  "description" : "The girls from Umamusume: Pretty Derby are back with a series of short adventures exploring their campus life. In this episode, Special Week is taking a strangely competitive makeup exam.\nSource: crunchyroll",
  "episode_id" : 230070,
  "length" : 3,
  "number" : 1,
  "rating" : {
    "rating" : 4.45,
    "total" : 4
  },
  "recap" : false,
  "resources" : {
    "CRUNCHY_ROLL" : [ "G60XNJ0PR" ]
  },
  "titles" : [ {
    "language" : "JAPANESE_TRANSLITERATED",
    "title" : "40 Tenka! Tracen Gakuen Tsuishi Tokubetsu"
  }, {
    "language" : "ENGLISH",
    "title" : "40% and Below! Tracen Academy Special Make-up Exams"
  }, {
    "language" : "JAPANESE",
    "title" : "40点下! トレセン学園追試特別"
  } ],
  "type" : "REGULAR"
}