{
  "air_date" : "2023-11-24",
  "anime_id" : 17918,
  "description" : "The Producer announces 283 Productions 1st Live, featuring all units. ALSTROEMERIA and The Hokago Climax Girls help promote the show by hosting a radio program.\nSource: crunchyroll",
  "episode_id" : 279038,
  "length" : 25,
  "number" : 8,
  "recap" : false,
  "resources" : {
    "CRUNCHY_ROLL" : [ "G14U47JJV" ]
  },
  "titles" : [ {
    "language" : "ENGLISH",
    "title" : "Shining Upon Each Other"
  }, {
    "language" : "JAPANESE_TRANSLITERATED",
    "title" : "Terashiau Keshiki"
  }, {
    "language" : "JAPANESE",
    "title" : "照らしあう景色"
  } ],
  "type" : "REGULAR"
}